supportinsightcheck/__init__.py
supportinsightcheck/main.py
supportinsightcheck/prompts.py
supportinsightcheck-2025.12.21110826.dist-info/METADATA
supportinsightcheck-2025.12.21110826.dist-info/WHEEL
supportinsightcheck-2025.12.21110826.dist-info/top_level.txt
supportinsightcheck-2025.12.21110826.dist-info/RECORD
