Metadata-Version: 2.4
Name: supportinsightcheck
Version: 2025.12.21110826
Summary: A new package that analyzes user-submitted text descriptions of customer service or technical support interactions to identify potential red flags that could lead to public complaints or negative expo
Author-email: supportinsightcheck <hi@eugene.plus>
License: MIT
Project-URL: Homepage, https://github.com/chigwell/supportinsightcheck
Requires-Python: >=3.9
Requires-Dist: langchain-llm7>=0.0.0
Requires-Dist: llmatch-messages>=0.0.0
Requires-Dist: langchain-core>=0.3.0
